kvom/__init__.py
kvom/exceptions.py
kvom/field.py
kvom/model.py
kvom/source.py
kvom/utils.py
kvom-0.2.0.dist-info/LICENSE
kvom-0.2.0.dist-info/WHEEL
kvom-0.2.0.dist-info/METADATA
kvom-0.2.0.dist-info/RECORD
